germaparlpy/__init__.py
germaparlpy/corpus.py
germaparlpy/utilities.py
germaparlpy-1.0.5.dist-info/METADATA
germaparlpy-1.0.5.dist-info/WHEEL
germaparlpy-1.0.5.dist-info/licenses/LICENSE
germaparlpy-1.0.5.dist-info/RECORD
