Metadata-Version: 2.4
Name: germaparlpy
Version: 1.0.5
Summary: The GermaParlPy Python package provides functionality to deserialize, serialize, manage, and query the GermaParlTEI corpus and derived corpora.
License: MIT
License-File: LICENSE
Author: Marlon-Benedikt George
Author-email: mbgdevelopment@proton.me
Requires-Python: >=3.9
Classifier: License :: OSI Approved :: MIT License
Classifier: Programming Language :: Python :: 3
Classifier: Programming Language :: Python :: 3.9
Classifier: Programming Language :: Python :: 3.10
Classifier: Programming Language :: Python :: 3.11
Classifier: Programming Language :: Python :: 3.12
Classifier: Programming Language :: Python :: 3.13
Classifier: Programming Language :: Python :: 3.14
Project-URL: Homepage, https://nolram567.github.io/GermaParlPy/
Project-URL: Issues, https://github.com/Nolram567/GermaParlPy/issues
Project-URL: Repository, https://github.com/Nolram567/GermaParlPy
